krakipy/__init__.py
krakipy/krakipy.py
krakipy/version.py
krakipy-0.1.11.dist-info/LICENSE
krakipy-0.1.11.dist-info/METADATA
krakipy-0.1.11.dist-info/WHEEL
krakipy-0.1.11.dist-info/top_level.txt
krakipy-0.1.11.dist-info/RECORD
