Metadata-Version: 2.1
Name: krakipy
Version: 0.1.11
Summary: A well-documented Python API for the Kraken Cryptocurrency Exchange
Home-page: https://krakipy.readthedocs.io/en/latest/
Author: Hubertus Wilisch
Author-email: aionoso-software@outlook.de
Project-URL: Source, https://github.com/Aionoso/Krakipy
Keywords: kraken api crypto finance bitcoin tor mit exchange
Classifier: Topic :: Internet :: WWW/HTTP
Classifier: Topic :: Security
Classifier: Topic :: Internet
Classifier: Topic :: Software Development
Classifier: Topic :: Office/Business :: Financial :: Investment
Classifier: Topic :: Utilities
Classifier: Topic :: Documentation :: Sphinx
Classifier: Development Status :: 5 - Production/Stable
Classifier: Intended Audience :: Developers
Classifier: Intended Audience :: Financial and Insurance Industry
Classifier: Intended Audience :: Information Technology
Classifier: Programming Language :: Python :: 3
Classifier: License :: OSI Approved :: MIT License
Classifier: Operating System :: OS Independent
Requires-Python: >=3.6
License-File: LICENSE
Requires-Dist: pandas>=0.17.0
Requires-Dist: requests
Requires-Dist: pyotp
Requires-Dist: torpy
